{
  "current": "Dota 2 (Immortal player), Honkai: Star Rail, Cyberpunk 2077",
  "previous": {
    "gacha": "Genshin Impact, Princess Connect! Re:Dive, Girls Cafe Guns 2, Arknights",
    "single": "Persona 5 Royal, The Witcher 3, Rise of the Tomb Raider, GTA 5 story mode, Portal / Portal 2, Ultimate Ninja Storm 4, Trine 2 ...",
    "multiple": "DotA, Starcraft 2, Warcraft 3, Overwatch, PUBG, Pummel Party, CSGO, Apex, ...",
    "mini": "Cuphead, Plants vs Zombies, Darkest Dungeon, Magic Tower series, South Park: The Stick of Truth, ...",
    "gal": "If My Heart Had Wings, Doki Doki Literature Club (?)"
  }
}